{
    "server_cpu":  14,
    "server_ram":  15.1,
    "feed":  [
                 {
                     "player":  "Pepitaaf",
                     "action":  "MAGENTA FLOATING CARPET",
                     "date":  "14:53",
                     "head":  "https://minotar.net/avatar/Pepitaaf/32"
                 },
                 {
                     "player":  "Chenchitoo",
                     "action":  "TUNGSTEN PICKAXE",
                     "date":  "02:24",
                     "head":  "https://minotar.net/avatar/Chenchitoo/32"
                 }
             ]
}
